dftracer/python/__init__.py
dftracer/python/_version.py
dftracer/python/ai.py
dftracer/python/ai_common.py
dftracer/python/ai_init.py
dftracer/python/common.py
dftracer/python/dynamo.py
dftracer/python/env.py
dftracer/python/logger.py
dftracer/python/py.typed
dftracer/python/dbg/__init__.py
dftracer/python/dbg/ai.py
dftracer/python/dbg/logger.py
pydftracer-2.0.2.dist-info/licenses/LICENSE
pydftracer-2.0.2.dist-info/METADATA
pydftracer-2.0.2.dist-info/WHEEL
pydftracer-2.0.2.dist-info/top_level.txt
pydftracer-2.0.2.dist-info/RECORD
