Metadata-Version: 2.4
Name: pydftracer
Version: 2.0.2
Summary: Python libs for DFTracer
Author-email: "Hariharan Devarajan (Hari)" <hariharandev1@llnl.gov>, Ray Andrew Sinurat <raydreww@gmail.com>
Maintainer-email: "Hariharan Devarajan (Hari)" <hariharandev1@llnl.gov>, Ray Andrew Sinurat <raydreww@gmail.com>
License: MIT
Project-URL: Homepage, https://github.com/LLNL/pydftracer
Project-URL: Repository, https://github.com/LLNL/pydftracer
Project-URL: Bug Tracker, https://github.com/LLNL/pydftracer/issues
Project-URL: Documentation, https://dftracer.readthedocs.io/en/latest/
Classifier: Development Status :: 3 - Alpha
Classifier: Intended Audience :: Science/Research
Classifier: Topic :: Software Development :: Build Tools
Classifier: License :: OSI Approved :: MIT License
Classifier: Programming Language :: Python :: 3.9
Classifier: Programming Language :: Python :: 3.10
Classifier: Programming Language :: Python :: 3.11
Classifier: Programming Language :: Python :: 3.12
Classifier: Programming Language :: Python :: 3 :: Only
Requires-Python: >=3.9
License-File: LICENSE
Provides-Extra: dev
Requires-Dist: pytest>=6.0; extra == "dev"
Requires-Dist: pytest-cov; extra == "dev"
Requires-Dist: pytest-xdist; extra == "dev"
Requires-Dist: h5py; extra == "dev"
Requires-Dist: numpy; extra == "dev"
Requires-Dist: pillow; extra == "dev"
Requires-Dist: ruff; extra == "dev"
Requires-Dist: mypy; extra == "dev"
Provides-Extra: dynamo
Requires-Dist: torch>=2.5.1; extra == "dynamo"
Provides-Extra: docs
Requires-Dist: sphinx>=5.0; extra == "docs"
Requires-Dist: sphinx-rtd-theme>=1.0; extra == "docs"
Requires-Dist: myst-parser>=0.18; extra == "docs"
Dynamic: license-file
